{ "compressionlevel":-1,
 "height":12,
 "infinite":false,
 "layers":[
        {
         "id":9,
         "layers":[
                {
                 "data":[0, 0, 0, 0, 0, 0, 0, 0, 0, 0, 0, 0, 0, 0, 0, 0, 0, 8477, 8477, 8477, 8477, 8477, 8477, 8477, 8477, 8477, 8477, 9055, 9055, 9055, 9055, 0, 0, 8669, 8669, 8669, 8669, 8669, 8669, 8669, 8669, 8669, 8669, 9247, 9247, 9247, 9247, 0, 0, 6554, 6554, 6554, 6554, 6554, 6554, 6554, 6554, 6554, 6554, 6554, 6554, 6554, 6554, 0, 0, 6554, 6554, 6554, 6554, 6554, 6554, 6554, 6554, 6554, 6554, 6554, 6554, 6554, 6554, 0, 0, 6554, 6554, 6554, 6554, 6554, 6554, 6554, 6554, 6554, 6554, 6554, 6554, 6554, 6554, 0, 0, 6554, 6554, 6554, 6554, 6554, 6554, 6554, 6554, 6554, 6554, 6554, 6554, 6554, 6554, 0, 0, 6554, 6554, 6554, 6554, 6554, 6554, 6554, 6554, 6554, 6554, 6554, 6554, 6554, 6554, 0, 0, 6554, 6554, 6554, 6554, 6554, 6554, 6554, 6554, 6554, 6554, 6554, 6554, 6554, 6554, 0, 0, 6554, 6554, 6554, 6554, 6554, 6554, 6554, 6554, 6554, 6554, 6554, 6554, 6554, 6554, 0, 0, 6554, 6554, 6554, 6554, 6554, 6554, 6554, 6554, 6554, 6554, 6554, 6554, 6554, 6554, 0, 0, 0, 0, 0, 0, 0, 0, 0, 0, 0, 0, 0, 0, 0, 0, 0],
                 "height":12,
                 "id":5,
                 "name":"Background",
                 "opacity":1,
                 "type":"tilelayer",
                 "visible":true,
                 "width":16,
                 "x":0,
                 "y":0
                }, 
                {
                 "data":[0, 0, 0, 0, 0, 0, 0, 0, 0, 0, 0, 0, 0, 0, 0, 0, 0, 7328, 2147490783, 0, 8476, 0, 7135, 0, 0, 2147490783, 0, 2147492124, 0, 7135, 2147490976, 0, 0, 7520, 2147490975, 0, 8478, 0, 7327, 0, 0, 2147490975, 0, 2147492126, 0, 7327, 2147491168, 0, 0, 0, 0, 10204, 10205, 10206, 0, 2147494814, 2147494813, 0, 10201, 10202, 10203, 0, 0, 0, 0, 0, 0, 10396, 10397, 10398, 0, 0, 0, 0, 10393, 10394, 10395, 0, 0, 0, 0, 0, 0, 10588, 10589, 10590, 0, 0, 0, 0, 10585, 10586, 10587, 0, 0, 0, 0, 0, 0, 0, 0, 0, 0, 0, 0, 0, 0, 0, 0, 0, 0, 0, 0, 0, 0, 0, 0, 0, 0, 0, 0, 0, 0, 0, 0, 0, 0, 0, 0, 0, 0, 0, 0, 0, 0, 0, 0, 0, 0, 0, 0, 0, 0, 0, 0, 0, 0, 0, 0, 0, 0, 0, 0, 0, 0, 0, 0, 0, 0, 0, 0, 0, 0, 0, 0, 0, 0, 6555, 6556, 0, 0, 0, 0, 0, 0, 0, 0, 0, 0, 0, 0, 0, 0, 0, 0, 0, 0, 0, 0, 0, 0, 0],
                 "height":12,
                 "id":7,
                 "name":"Details",
                 "opacity":1,
                 "type":"tilelayer",
                 "visible":true,
                 "width":16,
                 "x":0,
                 "y":0
                }],
         "name":"Maps Visuals",
         "opacity":1,
         "type":"group",
         "visible":true,
         "x":0,
         "y":0
        }, 
        {
         "id":8,
         "layers":[
                {
                 "data":[0, 0, 0, 0, 0, 0, 0, 0, 0, 0, 0, 0, 0, 0, 0, 0, 0, 1, 1, 1, 1, 1, 1, 1, 1, 1, 1, 1, 1, 1, 1, 0, 1, 0, 0, 0, 0, 0, 0, 1, 1, 0, 0, 0, 0, 0, 0, 1, 1, 0, 0, 0, 0, 0, 0, 0, 0, 0, 0, 0, 0, 0, 0, 1, 1, 0, 0, 0, 0, 0, 0, 0, 0, 0, 0, 0, 0, 0, 0, 1, 1, 0, 0, 0, 0, 0, 0, 0, 0, 0, 0, 0, 0, 0, 0, 1, 1, 0, 0, 0, 0, 0, 0, 0, 0, 0, 0, 0, 0, 0, 0, 1, 1, 0, 0, 0, 0, 0, 0, 0, 0, 0, 0, 0, 0, 0, 0, 1, 1, 0, 0, 0, 0, 0, 0, 0, 0, 0, 0, 0, 0, 0, 0, 1, 1, 0, 0, 0, 0, 0, 0, 0, 0, 0, 0, 0, 0, 0, 0, 1, 1, 0, 0, 0, 0, 0, 0, 0, 0, 0, 0, 0, 0, 0, 0, 1, 0, 1, 1, 1, 1, 1, 1, 1, 1, 1, 1, 1, 1, 1, 1, 0],
                 "height":12,
                 "id":1,
                 "name":"Colissions",
                 "opacity":0.1,
                 "type":"tilelayer",
                 "visible":true,
                 "width":16,
                 "x":0,
                 "y":0
                }, 
                {
                 "data":[0, 0, 0, 0, 0, 0, 0, 0, 0, 0, 0, 0, 0, 0, 0, 0, 0, 0, 0, 0, 0, 0, 0, 0, 0, 0, 0, 0, 0, 0, 0, 0, 0, 0, 0, 0, 0, 0, 0, 0, 0, 0, 0, 0, 0, 0, 0, 0, 0, 0, 0, 0, 0, 0, 0, 0, 0, 0, 0, 0, 0, 0, 0, 0, 0, 0, 0, 0, 0, 0, 0, 0, 0, 0, 0, 0, 0, 0, 0, 0, 0, 0, 0, 0, 0, 0, 0, 0, 0, 0, 0, 0, 0, 0, 0, 0, 0, 0, 0, 0, 0, 0, 0, 0, 0, 0, 0, 0, 0, 0, 0, 0, 0, 0, 0, 0, 0, 0, 0, 0, 0, 0, 0, 0, 0, 0, 0, 0, 0, 0, 0, 0, 0, 0, 0, 0, 0, 0, 0, 0, 0, 0, 0, 0, 0, 0, 0, 0, 0, 0, 0, 0, 0, 0, 0, 0, 0, 0, 0, 0, 0, 0, 0, 0, 0, 0, 0, 3, 3, 0, 0, 0, 0, 0, 0, 0, 0, 0, 0, 0, 0, 0, 0, 0, 0, 0, 0, 0, 0, 0, 0, 0],
                 "height":12,
                 "id":10,
                 "name":"Change Map",
                 "opacity":0.3,
                 "type":"tilelayer",
                 "visible":true,
                 "width":16,
                 "x":0,
                 "y":0
                }, 
                {
                 "data":[0, 0, 0, 0, 0, 0, 0, 0, 0, 0, 0, 0, 0, 0, 0, 0, 0, 0, 0, 0, 0, 0, 0, 0, 0, 0, 0, 0, 0, 0, 0, 0, 0, 0, 0, 0, 0, 0, 0, 0, 0, 0, 0, 0, 0, 0, 0, 0, 0, 0, 0, 0, 5, 0, 0, 0, 0, 0, 0, 5, 0, 0, 0, 0, 0, 0, 0, 0, 0, 0, 0, 0, 0, 0, 0, 0, 0, 0, 0, 0, 0, 0, 0, 0, 0, 0, 0, 0, 0, 0, 0, 0, 0, 0, 0, 0, 0, 0, 0, 0, 0, 0, 0, 0, 0, 0, 0, 0, 0, 0, 0, 0, 0, 0, 0, 0, 0, 0, 0, 0, 0, 0, 0, 0, 0, 0, 0, 0, 0, 0, 0, 0, 0, 0, 0, 0, 0, 0, 0, 0, 0, 0, 0, 0, 0, 0, 0, 0, 0, 0, 0, 0, 0, 0, 0, 0, 0, 0, 0, 0, 0, 0, 0, 0, 0, 0, 0, 0, 0, 0, 0, 0, 0, 0, 0, 0, 0, 0, 0, 0, 0, 0, 0, 0, 0, 0, 0, 0, 0, 0, 0, 0],
                 "height":12,
                 "id":11,
                 "name":"Event Zones",
                 "opacity":0.7,
                 "type":"tilelayer",
                 "visible":true,
                 "width":16,
                 "x":0,
                 "y":0
                }],
         "name":"Data",
         "opacity":1,
         "type":"group",
         "visible":true,
         "x":0,
         "y":0
        }],
 "nextlayerid":12,
 "nextobjectid":1,
 "orientation":"orthogonal",
 "renderorder":"right-down",
 "tiledversion":"1.8.2",
 "tileheight":16,
 "tilesets":[
        {
         "firstgid":1,
         "source":"..\/Tileset\/tsx\/Collisions.tsx"
        }, 
        {
         "firstgid":401,
         "source":"..\/Tileset\/tsx\/interior.tsx"
        }],
 "tilewidth":16,
 "type":"map",
 "version":"1.8",
 "width":16
}